mypolr/__init__.py
mypolr/__main__.py
mypolr/cli.py
mypolr/exceptions.py
mypolr/polr_api.py
mypolr-1.3.11.dist-info/DESCRIPTION.rst
mypolr-1.3.11.dist-info/LICENSE.txt
mypolr-1.3.11.dist-info/METADATA
mypolr-1.3.11.dist-info/RECORD
mypolr-1.3.11.dist-info/WHEEL
mypolr-1.3.11.dist-info/metadata.json
mypolr-1.3.11.dist-info/top_level.txt
