Metadata-Version: 2.0
Name: mypolr
Version: 1.3.11
Summary: Package to use with the Polr Project 's REST API. Can also be used from CLI.
Home-page: https://github.com/fauskanger/mypolr
Author: Thomas Fauskanger
Author-email: UNKNOWN
License: MIT
Download-URL: https://pypi.org/project/mypolr/#files
Keywords: polr-project shorturl api
Platform: UNKNOWN
Classifier: Development Status :: 5 - Production/Stable
Classifier: Intended Audience :: Developers
Classifier: Intended Audience :: Information Technology
Classifier: Intended Audience :: Other Audience
Classifier: License :: OSI Approved :: MIT License
Classifier: Programming Language :: Python :: 2.7
Classifier: Programming Language :: Python :: 3.3
Classifier: Programming Language :: Python :: 3.4
Classifier: Programming Language :: Python :: 3.5
Classifier: Programming Language :: Python :: 3.6
Classifier: Programming Language :: Python :: 3.7
Classifier: Topic :: Internet :: WWW/HTTP
Classifier: Topic :: Software Development
Classifier: Topic :: Utilities
Requires-Python: >=2.7,!=3.0.*,!=3.1.*,!=3.2.*
Requires-Dist: requests
